{
"type": "FeatureCollection",
"name": "camara",
"crs": { "type": "name", "properties": { "name": "urn:ogc:def:crs:OGC:1.3:CRS84" } },
"features": [
{ "type": "Feature", "properties": { "nombre": "Camara Forestal - Tejeda GC (simulada)", "lat": 27.9938, "lon": -15.5963, "descripcion": "Punto de vigilancia simulado en el termino municipal de Tejeda, area afectada por el incendio de agosto de 2023." }, "geometry": { "type": "Point", "coordinates": [ -15.5963, 27.9938 ] } }
]
}
